fight_detection/Fight_utils.py
fight_detection/__init__.py
fight_detection/model_16_m3_0.8888.pth
Feight_Detection_From_Surveillance_Cameras-0.0.1.dist-info/LICENCE
Feight_Detection_From_Surveillance_Cameras-0.0.1.dist-info/METADATA
Feight_Detection_From_Surveillance_Cameras-0.0.1.dist-info/WHEEL
Feight_Detection_From_Surveillance_Cameras-0.0.1.dist-info/top_level.txt
Feight_Detection_From_Surveillance_Cameras-0.0.1.dist-info/RECORD
