Metadata-Version: 2.1
Name: Feight-Detection-From-Surveillance-Cameras
Version: 0.0.1
Summary: Detection Fight or Not
Home-page: https://github.com/MohamedSebaie/Fight_Detection_From_Surveillance_Cameras-PyTorch_Project
Author: The Innovators
Author-email: mohamed.sebaie1@gmail.com
License: UNKNOWN
Platform: UNKNOWN
Classifier: Programming Language :: Python :: 3
Classifier: License :: OSI Approved :: MIT License
Classifier: Operating System :: OS Independent
Requires-Python: >=3.7
License-File: LICENCE
